oas_client/__init__.py
oas_client/__main__.py
oas_client/parser.py
oas_client/py.typed
oas_client/types.py
oas_client/utils.py
oas_client/renderers/__init__.py
oas_client/renderers/client.py
oas_client/renderers/params.py
oas_client/renderers/queries.py
oas_client/renderers/requests.py
oas_client/renderers/responses.py
oas_client/templates/client.jinja2
oas_client/templates/schemas.jinja2
oas_client-0.1.7.dist-info/licenses/LICENSE
oas_client-0.1.7.dist-info/METADATA
oas_client-0.1.7.dist-info/WHEEL
oas_client-0.1.7.dist-info/entry_points.txt
oas_client-0.1.7.dist-info/top_level.txt
oas_client-0.1.7.dist-info/RECORD
