Metadata-Version: 2.4
Name: oas-client
Version: 0.1.7
Summary: Generate typed python client from OpenAPI specification
Author-email: Pradish Bijukchhe <pradish@sandbox.com.np>
License: Copyright (c) 2025 Pradish Bijukchhe
Project-URL: Homepage, https://github.com/sandbox-pokhara/oas-client
Project-URL: Issues, https://github.com/sandbox-pokhara/oas-client/issues
Classifier: Programming Language :: Python :: 3
Requires-Python: >=3.11
License-File: LICENSE
Requires-Dist: httpx>=0.22.0
Requires-Dist: jinja2>=2.11.3
Requires-Dist: typing-extensions>=4.7.1
Provides-Extra: pre-commit
Requires-Dist: pre-commit; extra == "pre-commit"
Dynamic: license-file
